readthedocs_ext/__init__.py
readthedocs_ext/embed.py
readthedocs_ext/external_version_warning.py
readthedocs_ext/readthedocs.py
readthedocs_ext/template-meta.py
readthedocs_ext/versionwarning.py
readthedocs_ext/_templates/readthedocs-insert.html.tmpl
readthedocs_sphinx_ext-2.2.5.dist-info/LICENSE
readthedocs_sphinx_ext-2.2.5.dist-info/METADATA
readthedocs_sphinx_ext-2.2.5.dist-info/WHEEL
readthedocs_sphinx_ext-2.2.5.dist-info/top_level.txt
readthedocs_sphinx_ext-2.2.5.dist-info/RECORD
