Metadata-Version: 2.1
Name: readthedocs-sphinx-ext
Version: 2.2.5
Summary: Sphinx extension for Read the Docs overrides
Home-page: http://github.com/readthedocs/readthedocs-sphinx-ext
Author: Read the Docs, Inc
Author-email: dev@readthedocs.com
License: MIT
License-File: LICENSE
Requires-Dist: requests
Requires-Dist: Jinja2 >=2.9
Requires-Dist: packaging
